PyEPnP.cpython-37m-darwin.so
PyEPnP-0.0.5.dist-info/LICENSE
PyEPnP-0.0.5.dist-info/METADATA
PyEPnP-0.0.5.dist-info/WHEEL
PyEPnP-0.0.5.dist-info/top_level.txt
PyEPnP-0.0.5.dist-info/RECORD
